src/.env
src/__init__.py
src/apiKey.py
src/app.py
src/domain.py
levdomain-1.1.8.dist-info/METADATA
levdomain-1.1.8.dist-info/WHEEL
levdomain-1.1.8.dist-info/entry_points.txt
levdomain-1.1.8.dist-info/top_level.txt
levdomain-1.1.8.dist-info/RECORD
